exam_practice/__init__.py
exam_practice/exam_practice.py
exam_practice-0.0.2.dist-info/LICENSE
exam_practice-0.0.2.dist-info/METADATA
exam_practice-0.0.2.dist-info/WHEEL
exam_practice-0.0.2.dist-info/top_level.txt
exam_practice-0.0.2.dist-info/RECORD
